vcli/__init__.py
vcli/completion_refresher.py
vcli/config.py
vcli/encodingutils.py
vcli/key_bindings.py
vcli/magic.py
vcli/main.py
vcli/vbuffer.py
vcli/vclirc
vcli/vcompleter.py
vcli/verror.py
vcli/vexecute.py
vcli/vstyle.py
vcli/vtoolbar.py
vcli/packages/__init__.py
vcli/packages/counter.py
vcli/packages/expanded.py
vcli/packages/ordereddict.py
vcli/packages/parseutils.py
vcli/packages/sqlcompletion.py
vcli/packages/tabulate.py
vcli/packages/vtablefmt.py
vcli/packages/vspecial/__init__.py
vcli/packages/vspecial/dbcommands.py
vcli/packages/vspecial/iocommands.py
vcli/packages/vspecial/main.py
vcli/packages/vspecial/namedqueries.py
vcli-0.1.1.dist-info/DESCRIPTION.rst
vcli-0.1.1.dist-info/entry_points.txt
vcli-0.1.1.dist-info/METADATA
vcli-0.1.1.dist-info/metadata.json
vcli-0.1.1.dist-info/RECORD
vcli-0.1.1.dist-info/top_level.txt
vcli-0.1.1.dist-info/WHEEL
